cannonball/__init__.py
cannonball-0.0.1.dist-info/METADATA
cannonball-0.0.1.dist-info/WHEEL
cannonball-0.0.1.dist-info/top_level.txt
cannonball-0.0.1.dist-info/RECORD
